[
  {
    "id": "f8c5f4fb3f8b590c",
    "type": "your-node",
    "z": "dd3a427256d642e5",
    "g": "4a6cd837c0a05afd",
    "name": "your-node",
    "myProperty": {
      "type": "str",
      "value": ""
    },
    "myProperty2": {
      "type": "str",
      "value": ""
    },
    "remoteServer": "85734d87be7310ea",
    "anotherRemoteServer": "db7962bb4d73eb96",
    "country": "brazil",
    "fruit": ["apple", "melon"],
    "number": "1",
    "object": ["{\"test\":\"a\"}", "{\"test\":\"b\"}"],
    "array": "[\"a\"]",
    "jsontest": "{\n    \"b\" : \"b\"\n}",
    "csstest": "",
    "x": 490,
    "y": 300,
    "wires": [["4d7e6b2f7ccc00f8"]]
  },
  {
    "id": "85734d87be7310ea",
    "type": "remote-server",
    "name": "remote-server-1",
    "host": "localhost"
  },
  {
    "id": "db7962bb4d73eb96",
    "type": "remote-server",
    "name": "remote-server-2",
    "host": "localhost"
  }
]
